{
  "name": "Archchess",
  "description": "An old variant by Dr. Francesco Piacenza. 10x10 board with two added pieces, one that moves one step diagonally, the other jumps two squares orthogonally, diagonally, or as a Knight.\nhttps://www.chessvariants.com/historic.dir/arch.html",
  "width": 10,
  "height": 10,
  "promotions": ["queen"],
  "pieces": [
	{
		"x": 0,"xlen": 10,"y": 1,"side": "white","piece": "pawn"	
	},
    {
		"x": 0,"xlen": 10,"y": 8,"side": "black","piece": "pawn"
	},
	
    {
		"x": 0,"y": 0,"side": "white","piece": "rook"
	},
    {
		"x": 9,"y": 0,"side": "white","piece": "rook"
	},
    {
		"x": 0,"y": 9,"side": "black","piece": "rook"
	},
    {
		"x": 9,"y": 9,"side": "black","piece": "rook"
	},
	
	{
		"x": 1,"y": 0,"side": "white","piece": "knight"
	},
	{
		"x": 8,"y": 0,"side": "white","piece": "knight"
	},
	{
		"x": 1,"y": 9,"side": "black","piece": "knight"
	},
	{
		"x": 8,"y": 9,"side": "black","piece": "knight"
	},
	
	{
		"x": 2,"y": 0,"side": "white","piece": "bishop"
	},
	{
		"x": 7,"y": 0,"side": "white","piece": "bishop"
	},
	{
		"x": 2,"y": 9,"side": "black","piece": "bishop"
	},
	{
		"x": 7,"y": 9,"side": "black","piece": "bishop"
	},
	
	{
		"x": 3,"y": 0,"side": "white","piece": "squirrel"
	},
	{
		"x": 3,"y": 9,"side": "black","piece": "squirrel"
	},
	
	{
		"x": 4,"y": 0,"side": "white","piece": "king_arch"
	},
	{
		"x": 4,"y": 9,"side": "black","piece": "king_arch"
	},
	
	{
		"x": 5,"y": 0,"side": "white","piece": "queen"
	},
	{
		"x": 5,"y": 9,"side": "black","piece": "queen"
	},
	
	{
		"x": 6,"y": 0,"side": "white","piece": "ferz"
	},
	{
		"x": 6,"y": 9,"side": "black","piece": "ferz"
	}
	
  ]
}